fity.py
setup.py
fity/__init__.py
fity/audio.py
fity/base.py
fity/categories.py
fity/extensible_markup.py
fity/fonts.py
fity/images.py
fity/matroska.py
fity/office.py
fity/portable_documents.py
fity/scripts.py
fity/unicode.py
fity/video.py
fity.egg-info/PKG-INFO
fity.egg-info/SOURCES.txt
fity.egg-info/dependency_links.txt
fity.egg-info/requires.txt
fity.egg-info/top_level.txt
fity/archives/__init__.py
fity/archives/base.py
fity/archives/bzip2open.py
fity/archives/gzipopen.py
fity/archives/raropen.py
fity/archives/taropen.py
fity/archives/types.py
fity/archives/zipopen.py