Metadata-Version: 1.1
Name: fity
Version: 0.1
Summary: Detect file types based on file content.
Home-page: https://github.com/alvra/fity
Author: Alexander van Ratingen
Author-email: alexander@van-ratingen.nl
License: UNKNOWN
Platform: UNKNOWN
Classifier: Operating System :: OS Independent
Classifier: Programming Language :: Python
Classifier: Programming Language :: Python :: 2
Classifier: Programming Language :: Python :: 3
Classifier: Development Status :: 5 - Production/Stable
Classifier: Intended Audience :: Developers
Classifier: License :: OSI Approved :: GNU General Public License v3 (GPLv3)
